
{
    "title": "上坝村的河道里到处是垃圾，它们将会被冲到下游",
    "link" : "/article/2023/0131.json"
}{
    "title": "玥玥主动帮我洗碗，她还要做垃圾分类",
    "link" : "/article/2023/0130.json"
}{
    "title": "上坝村每口山泉水旁边都会有农药垃圾存在",
    "link" : "/article/2023/0129a.json"
}{
    "title": "上坝村水源地垃圾随处可见，这已经成为了常态",
    "link" : "/article/2023/0129.json"
}{
    "title": "富川脐橙被当垃圾丢河里让水冲走，玥玥却在河里捞垃圾",
    "link" : "/article/2023/0128b.json"
}{
    "title": "农村垃圾分类势在必行，我又该如何去做",
    "link" : "/article/2023/0128a.json"
}{
    "title": "茜茜拿了一大包沙琪玛过来，她主动分了一半给我",
    "link" : "/article/2023/0128.json"
}{
    "title": "玥玥还这么小就知道垃圾分类，不乱丢垃圾",
    "link" : "/article/2023/0126.json"
}{
    "title": "玥玥默默地帮别人把被风吹走的小灯笼挂回去",
    "link" : "/article/2023/0125.json"
}{
    "title": "玥玥说她不想死，不想上坝村里有人死",
    "link" : "/article/2023/0121.json"
}
